passwork/__init__.py
passwork/main.py
passwork/passwork_api.py
passwork/session_options.py
passwork/password_crud/__init__.py
passwork/password_crud/add_password.py
passwork/password_crud/delete_password.py
passwork/password_crud/get_password.py
passwork/password_crud/search_password.py
passwork/rest_modules/__init__.py
passwork/rest_modules/passwords.py
passwork/rest_modules/users.py
passwork/rest_modules/vaults.py
passwork/utils/__init__.py
passwork/utils/base32.py
passwork/utils/crypto_file.py
passwork/utils/crypto_interface.py
passwork/utils/passwork_utils.py
passworktest-0.0.2.dist-info/LICENSE
passworktest-0.0.2.dist-info/METADATA
passworktest-0.0.2.dist-info/WHEEL
passworktest-0.0.2.dist-info/top_level.txt
passworktest-0.0.2.dist-info/RECORD
