Metadata-Version: 2.1
Name: passworktest
Version: 0.0.2
Summary: Passwork connector
Classifier: Programming Language :: Python :: 3.10
Classifier: License :: OSI Approved :: MIT License
Classifier: Operating System :: OS Independent
Requires-Python: >=3.10
License-File: LICENSE
Requires-Dist: requests >=2.31.0
Requires-Dist: cryptography >=42.0.5
Requires-Dist: loguru >=0.7.2
